imgease/__init__.py
imgease/convert.py
imgease/grayscale.py
imgease-0.2.0.dist-info/METADATA
imgease-0.2.0.dist-info/WHEEL
imgease-0.2.0.dist-info/entry_points.txt
imgease-0.2.0.dist-info/RECORD
