Metadata-Version: 2.1
Name: imgease
Version: 0.2.0
Summary: A collection of CLI tools for image processing.
Author: am2b
Requires-Python: >=3.12,<4.0
Classifier: Programming Language :: Python :: 3
Classifier: Programming Language :: Python :: 3.12
Requires-Dist: pillow (>=10.4.0,<11.0.0)
